logbt/__init__.py
logbt-0.4.0.dist-info/METADATA
logbt-0.4.0.dist-info/WHEEL
logbt-0.4.0.dist-info/RECORD
